dea_tools/__init__.py
dea_tools/__main__.py
dea_tools/bandindices.py
dea_tools/bom.py
dea_tools/classification.py
dea_tools/coastal.py
dea_tools/dask.py
dea_tools/datahandling.py
dea_tools/landcover.py
dea_tools/maps.py
dea_tools/plotting.py
dea_tools/spatial.py
dea_tools/temporal.py
dea_tools/validation.py
dea_tools/waterbodies.py
dea_tools/wetlands.py
dea_tools/app/__init__.py
dea_tools/app/animations.py
dea_tools/app/changefilmstrips.py
dea_tools/app/crophealth.py
dea_tools/app/deacoastlines.py
dea_tools/app/geomedian.py
dea_tools/app/imageexport.py
dea_tools/app/miningrehab.py
dea_tools/app/wetlandsinsighttool.py
dea_tools/app/widgetconstructors.py
dea_tools/mosaics/README.md
dea_tools/mosaics/__init__.py
dea_tools/mosaics/cog.py
dea_tools/mosaics/styling.py
dea_tools/mosaics/utils.py
dea_tools/mosaics/vrt.py
dea_tools-0.4.7.dist-info/METADATA
dea_tools-0.4.7.dist-info/WHEEL
dea_tools-0.4.7.dist-info/entry_points.txt
dea_tools-0.4.7.dist-info/licenses/LICENSE
dea_tools-0.4.7.dist-info/RECORD
