Metadata-Version: 2.4
Name: dea-tools
Version: 0.4.7
Summary: Open-source tools for geospatial analysis with Digital Earth Australia, Open Data Cube, and Xarray
Project-URL: Homepage, https://knowledge.dea.ga.gov.au/notebooks/Tools/
Project-URL: Repository, https://github.com/GeoscienceAustralia/dea-notebooks
Author-email: Geoscience Australia <earth.observation@ga.gov.au>
License-Expression: Apache-2.0
License-File: LICENSE
Keywords: datacube,digital earth australia,earth observation,geospatial analysis,remote sensing,satellite data
Classifier: Development Status :: 3 - Alpha
Classifier: Intended Audience :: Science/Research
Classifier: License :: OSI Approved :: Apache Software License
Classifier: Programming Language :: Python
Classifier: Programming Language :: Python :: 3
Classifier: Programming Language :: Python :: 3.10
Classifier: Programming Language :: Python :: 3.11
Classifier: Programming Language :: Python :: 3.12
Classifier: Programming Language :: Python :: 3.13
Classifier: Topic :: Scientific/Engineering :: GIS
Requires-Python: <4.0,>=3.10
Requires-Dist: aiohttp>=3.5.0
Requires-Dist: click>=8.0.0
Requires-Dist: dask-ml>=2023.3.24
Requires-Dist: dask>=2023.1.0
Requires-Dist: eo-tides>=0.8.2
Requires-Dist: fiona>=1.10.0
Requires-Dist: folium>=0.16.0
Requires-Dist: geopandas>=0.10.0
Requires-Dist: geopy>=2.0.0
Requires-Dist: imageio>=2.20.0
Requires-Dist: joblib>=1.0.0
Requires-Dist: lxml>=5.0.0
Requires-Dist: matplotlib>=3.8.0
Requires-Dist: numba>=0.57.0
Requires-Dist: numpy>=1.26.0
Requires-Dist: odc-algo>=1.1.1
Requires-Dist: odc-geo[tiff]>=0.4.7
Requires-Dist: odc-io>=0.2.2
Requires-Dist: odc-stac[botocore]>=0.3.0
Requires-Dist: owslib>=0.26.0
Requires-Dist: packaging>=22.0
Requires-Dist: pandas>=2.2.0
Requires-Dist: planetary-computer>=1.0.0
Requires-Dist: pyproj>=3.7.0
Requires-Dist: pystac-client>=0.8.3
Requires-Dist: python-dateutil>=2.8.2
Requires-Dist: pytz>=2022.1
Requires-Dist: rasterio>=1.3.11
Requires-Dist: rasterstats>=0.16.0
Requires-Dist: requests>=2.25.0
Requires-Dist: rioxarray>=0.10.0
Requires-Dist: s3fs>=2024.9.0
Requires-Dist: scikit-image>=0.22.0
Requires-Dist: scikit-learn>=1.4.0
Requires-Dist: scipy>=1.14.1
Requires-Dist: seaborn>=0.10.0
Requires-Dist: shapely>=2.0.5
Requires-Dist: tqdm>=4.55.0
Requires-Dist: traitlets>=5.0.0
Requires-Dist: xarray>=2022.3.0
Provides-Extra: all
Requires-Dist: affine>=2.3.1; extra == 'all'
Requires-Dist: beautifulsoup4>=4.12.0; extra == 'all'
Requires-Dist: cmocean>=3.0.0; extra == 'all'
Requires-Dist: contextily>=1.3.0; extra == 'all'
Requires-Dist: dask-gateway>=2023.1.0; extra == 'all'
Requires-Dist: dask-labextension>=7.0.0; extra == 'all'
Requires-Dist: datacube-ows>=1.9.3; extra == 'all'
Requires-Dist: datacube>=1.8.5; extra == 'all'
Requires-Dist: gcsfs>=2022.1.0; extra == 'all'
Requires-Dist: ipyleaflet>=0.17.0; extra == 'all'
Requires-Dist: jupyter-resource-usage>=1.0.0; extra == 'all'
Requires-Dist: jupyter>=1.0.0; extra == 'all'
Requires-Dist: odc-ui>=0.2.1; extra == 'all'
Requires-Dist: opencv-python>=4.6.0.66; extra == 'all'
Requires-Dist: pydotplus>=2.0.0; extra == 'all'
Requires-Dist: statsmodels>=0.14.0; extra == 'all'
Requires-Dist: sunriset>=1.0.0; extra == 'all'
Provides-Extra: dask-gateway
Requires-Dist: dask-gateway>=2023.1.0; extra == 'dask-gateway'
Provides-Extra: datacube
Requires-Dist: datacube-ows>=1.9.3; extra == 'datacube'
Requires-Dist: datacube>=1.8.5; extra == 'datacube'
Requires-Dist: odc-ui>=0.2.1; extra == 'datacube'
Provides-Extra: jupyter
Requires-Dist: dask-labextension>=7.0.0; extra == 'jupyter'
Requires-Dist: ipyleaflet>=0.17.0; extra == 'jupyter'
Requires-Dist: jupyter-resource-usage>=1.0.0; extra == 'jupyter'
Requires-Dist: jupyter>=1.0.0; extra == 'jupyter'
Provides-Extra: notebooks
Requires-Dist: affine>=2.3.1; extra == 'notebooks'
Requires-Dist: beautifulsoup4>=4.12.0; extra == 'notebooks'
Requires-Dist: cmocean>=3.0.0; extra == 'notebooks'
Requires-Dist: contextily>=1.3.0; extra == 'notebooks'
Requires-Dist: dask-labextension>=7.0.0; extra == 'notebooks'
Requires-Dist: gcsfs>=2022.1.0; extra == 'notebooks'
Requires-Dist: ipyleaflet>=0.17.0; extra == 'notebooks'
Requires-Dist: jupyter-resource-usage>=1.0.0; extra == 'notebooks'
Requires-Dist: jupyter>=1.0.0; extra == 'notebooks'
Requires-Dist: opencv-python>=4.6.0.66; extra == 'notebooks'
Requires-Dist: pydotplus>=2.0.0; extra == 'notebooks'
Requires-Dist: statsmodels>=0.14.0; extra == 'notebooks'
Requires-Dist: sunriset>=1.0.0; extra == 'notebooks'
